[
  {
    "bookSourceGroup": "ðŸ§©å°è¯´ðŸ’¬",
    "bookSourceName": "ðŸ§©SMå°è¯´",
    "bookSourceType": 0,
    "bookSourceUrl": "https://www.smxiaoshuo.net/",
    "customOrder": 886,
    "enabled": false,
    "enabledCookieJar": true,
    "enabledExplore": false,
    "exploreUrl": "å…¨éƒ¨ðŸª™::/book/category/page/{{page}}\néƒ½å¸‚ðŸª™::/book/category/tags/1/page/{{page}}\nå¤å…¸ðŸª™::/book/category/tags/2/page/{{page}}\næ­¦ä¾ ðŸª™::/book/category/tags/3/page/{{page}}\nåŽ†å²ðŸª™::/book/category/tags/4/page/{{page}}\nä¹¡åœŸðŸª™::/book/category/tags/5/page/{{page}}\nè¨€æƒ…ðŸª™::/book/category/tags/6/page/{{page}}\nè€½ç¾ŽðŸª™::/book/category/tags/7/page/{{page}}\næ ¡å›­ðŸª™::/book/category/tags/8/page/{{page}}\nçŽ„å¹»ðŸª™::/book/category/tags/9/page/{{page}}\nå®˜åœºðŸª™::/book/category/tags/10/page/{{page}}\nå¥³å°ŠðŸª™::/book/category/tags/11/page/{{page}}\nç©¿è¶ŠðŸª™::/book/category/tags/12/page/{{page}}\næƒŠæ‚šðŸª™::/book/category/tags/13/page/{{page}}\nåŒäººðŸª™::/book/category/tags/14/page/{{page}}",
    "header": "{\n\t\"User-Agent\":\"Mozilla/5.0 (Linux; Android 10; K) AppleWebKit/537.36 (KHTML, like Gecko) Chrome/116.0.0.0 Mobile Safari/537.36\"\n}",
    "lastUpdateTime": 1716552218583,
    "respondTime": 1907,
    "ruleBookInfo": {
      "coverUrl": "dt@img@src",
      "lastChapter": "p.title-c.0@text"
    },
    "ruleContent": {
      "content": "#BookText@html"
    },
    "ruleExplore": [],
    "ruleSearch": {
      "author": "class.book-module@text##Â·.*",
      "bookList": "class.common-list common-list-one",
      "bookUrl": "a@href",
      "coverUrl": "img@data-original",
      "intro": "class.book-profile@text",
      "kind": "class.book-module@text##.*Â·Â·",
      "name": "dt@text\n@js:\nresult.replace(/(.*$)/,\"$1\\tâˆ½\\tðŸ§©SMå°è¯´\")"
    },
    "ruleToc": {
      "chapterList": "#chapterlist > li",
      "chapterName": "a@text",
      "chapterUrl": "a@href"
    },
    "searchUrl": "https://www.smxiaoshuo.net/book/search?action=search&key={{key}}",
    "weight": 0
  }
]