[
  {
    "bookSourceComment": "//无标签页\n同站：\n新御书屋 \nhttps://m.u9mm.com\n耽美小说 \nhttps://m.danmei.info\n肉书阁   \nhttps://m.roushuge.com\n新御宅屋 \nhttps://m.xyuzhaiwu3.com https://m.xyuzhaiwu5.com\nhttps://m.xyuzhaiwu7.com",
    "bookSourceGroup": "",
    "bookSourceName": "PO脸红❤️",
    "bookSourceType": 0,
    "bookSourceUrl": "https://m.po18bb.com",
    "customOrder": 118,
    "enabled": true,
    "enabledCookieJar": false,
    "enabledExplore": true,
    "exploreUrl": "   最 新    ::/wapsort/0_{{page}}.html\n玄幻奇幻::/wapsort/1_{{page}}.html\n武侠仙侠::/wapsort/2_{{page}}.html\n都市言情::/wapsort/3_{{page}}.html\n科幻网游::/wapsort/4_{{page}}.html\n惊悚悬疑::/wapsort/5_{{page}}.html\n耽美同人::/wapsort/6_{{page}}.html\n穿越架空::/wapsort/7_{{page}}.html\n高辣浓情::/wapsort/8_{{page}}.html\n禁忌百合::/wapsort/9_{{page}}.html\n精品文学::/wapsort/10_{{page}}.html",
    "lastUpdateTime": "1723298275107",
    "respondTime": 180000,
    "ruleBookInfo": {
      "author": ".article_info_td.0@div.0@text",
      "init": "",
      "intro": "pre@text",
      "kind": ".article_info_td.0@div.1:3@text##类别：",
      "lastChapter": ".article_info_td.0@a.1@text",
      "name": "[style=\"background:none;\"]@text",
      "tocUrl": "[style=\"color:red;\"]@href",
      "wordCount": "##总字数：([^<]+)<##$1###@js:result+'字'"
    },
    "ruleContent": {
      "content": "#nr1@html"
    },
    "ruleExplore": {
      "author": "",
      "bookList": "",
      "bookUrl": "",
      "coverUrl": "",
      "intro": "",
      "kind": "",
      "name": ""
    },
    "ruleReview": [],
    "ruleSearch": {
      "author": "strong@text",
      "bookList": ".common-bookele",
      "bookUrl": "a.1@href",
      "checkKeyWord": "",
      "coverUrl": "@js:'https://m.powenwu8.com/images/nocover.jpg'",
      "intro": ".abstract@text",
      "kind": ".lastupdate@text##栏目：",
      "name": ".articlename@text||h3@text"
    },
    "ruleToc": {
      "chapterList": "ul@li!-1@a",
      "chapterName": "text",
      "chapterUrl": "href"
    },
    "searchUrl": "/s.php,{\n'charset': '',\n'method': 'POST',\n'body': 'type=articlename&s={{key}}'\n}",
    "weight": 0
  }
]