[
  {
    "bookSourceComment": "",
    "bookSourceGroup": "",
    "bookSourceName": "小说虎",
    "bookSourceType": 0,
    "bookSourceUrl": "https://m.xshbook.com/",
    "bookUrlPattern": "",
    "customOrder": 0,
    "enabled": true,
    "enabledCookieJar": true,
    "enabledExplore": true,
    "exploreScreen": "",
    "exploreUrl": "                      默认                      ::\n所有::/fenlei/{{page}}/\n玄幻::/fenlei/1/{{page}}\n奇幻::/fenlei/2/{{page}}\n武侠::/fenlei/3/{{page}}\n仙侠::/fenlei/4/{{page}}\n都市::/fenlei/5/{{page}}\n军事::/fenlei/6/{{page}}\n历史::/fenlei/7/{{page}}\n游戏::/fenlei/8/{{page}}\n竞技::/fenlei/9/{{page}}\n科幻::/fenlei/10/{{page}}\n悬疑::/fenlei/11/{{page}}\n灵异::/fenlei/12/{{page}}\n其他::/fenlei/13/{{page}}\n古代言情::/fenlei/14/{{page}}\n仙侠奇缘::/fenlei/15/{{page}}\n现代言情::/fenlei/16/{{page}}\n浪漫青春::/fenlei/17/{{page}}\n玄幻言情::/fenlei/18/{{page}}\n悬疑灵异::/fenlei/19/{{page}}\n科幻空间::/fenlei/20/{{page}}\n游戏竞技::/fenlei/21/{{page}}\nBL文::/fenlei/22/{{page}}\nGL文::/fenlei/23/{{page}}\n二次元::/fenlei/24/{{page}}\n                      完本                      ::\n所有::/quanben/fenlei/{{page}}/\n玄幻::/quanben/fenlei/1/{{page}}\n奇幻::/quanben/fenlei/2/{{page}}\n武侠::/quanben/fenlei/3/{{page}}\n仙侠::/quanben/fenlei/4/{{page}}\n都市::/quanben/fenlei/5/{{page}}\n军事::/quanben/fenlei/6/{{page}}\n历史::/quanben/fenlei/7/{{page}}\n游戏::/quanben/fenlei/8/{{page}}\n竞技::/quanben/fenlei/9/{{page}}\n科幻::/quanben/fenlei/10/{{page}}\n悬疑::/quanben/fenlei/11/{{page}}\n灵异::/quanben/fenlei/12/{{page}}\n其他::/quanben/fenlei/13/{{page}}\n古代言情::/quanben/fenlei/14/{{page}}\n仙侠奇缘::/quanben/fenlei/15/{{page}}\n现代言情::/quanben/fenlei/16/{{page}}\n浪漫青春::/quanben/fenlei/17/{{page}}\n玄幻言情::/quanben/fenlei/18/{{page}}\n悬疑灵异::/quanben/fenlei/19/{{page}}\n科幻空间::/quanben/fenlei/20/{{page}}\n游戏竞技::/quanben/fenlei/21/{{page}}\nBL文::/quanben/fenlei/22/{{page}}\nGL文::/quanben/fenlei/23/{{page}}\n二次元::/quanben/fenlei/24/{{page}}",
    "lastUpdateTime": "1725042568027",
    "respondTime": 180000,
    "ruleBookInfo": {
      "author": "//*[@id=\"info\"]/p[1]/text()",
      "coverUrl": "",
      "init": "",
      "intro": "",
      "kind": "{{//*[@class=\"con_top\"]//a[2]/text()}} {{//*[contains(text(), \"新:\")][1]//text()##最后更新:}}",
      "lastChapter": "{{//*[contains(text(), \"新:\")][2]//a//text()}} ",
      "name": "//*[@id=\"info\"]/h1/text()"
    },
    "ruleContent": {
      "content": "//*[@id=\"content\"]/html()",
      "nextContentUrl": ""
    },
    "ruleExplore": {
      "author": "//*[@class=\"b\"]/text()",
      "bookList": "//*[@class=\"CGsectionTwo-right-content-unit\"]",
      "bookUrl": "{{baseUrl=baseUrl\n.replace(/m\\.(.*)\\/fenlei[\\/\\d]+/,\"www.$1\")\n.replace(\"/quanben\",\"\")}}{{//*[@class='title']/@href}}\n\n",
      "coverUrl": "",
      "intro": "{{//*[@class=\"CGsectionTwo-right-content-unit\"]/p[3]/text()}}",
      "kind": "//p[4]/text()",
      "lastChapter": "",
      "name": "//*[@class='title']/text()"
    },
    "ruleSearch": {
      "author": "//dt//span/text()",
      "bookList": "//div[@class=\"item\"]",
      "bookUrl": "//dt//a/@href",
      "checkKeyWord": "复苏之秘",
      "coverUrl": "//img/@src",
      "intro": "//dd/text()",
      "name": "//dt//a/text()"
    },
    "ruleToc": {
      "chapterList": "//*[@id=\"list\"]//dd",
      "chapterName": "//a/text()",
      "chapterUrl": "//a/@href"
    },
    "searchUrl": "https://www.sososhu.com/?q={{key}}&site=xshbook,{\"webView\": true}",
    "variableComment": "",
    "weight": 0
  }
]